mikro/__init__.py
mikro/api/__init__.py
mikro/api/schema.py
mikro/contrib/__init__.py
mikro/contrib/fakts/__init__.py
mikro/contrib/fakts/datalayer.py
mikro/datalayer.py
mikro/errors.py
mikro/funcs.py
mikro/links/__init__.py
mikro/links/datalayer.py
mikro/links/errors.py
mikro/mikro.py
mikro/rath.py
mikro/scalars.py
mikro/structures.py
mikro/testing/__init__.py
mikro/testing/datalayer.py
mikro/traits.py
mikro/utils.py
mikro/widgets.py
mikro-0.3.95.dist-info/METADATA
mikro-0.3.95.dist-info/WHEEL
mikro-0.3.95.dist-info/RECORD
