Metadata-Version: 2.1
Name: mikro
Version: 0.3.95
Summary: images for arkitekt
License: CC BY-NC 3.0
Author: jhnnsrs
Author-email: jhnnsrs@gmail.com
Requires-Python: >=3.8,<4.0
Classifier: License :: Other/Proprietary License
Classifier: Programming Language :: Python :: 3
Classifier: Programming Language :: Python :: 3.8
Classifier: Programming Language :: Python :: 3.9
Classifier: Programming Language :: Python :: 3.10
Classifier: Programming Language :: Python :: 3.11
Provides-Extra: turms
Requires-Dist: dask (>=2023.3.0)
Requires-Dist: pandas (>=1.5.3)
Requires-Dist: pyarrow (>=11.0)
Requires-Dist: rath (>=0.5.0)
Requires-Dist: s3fs (>=2023.1.0)
Requires-Dist: xarray (>=2022.12.0)
Requires-Dist: zarr (>=2.14.2)
